detech_query_pkg/__init__.py
detech_query_pkg/dynamodb_pkg/__init__.py
detech_query_pkg/dynamodb_pkg/dynamodb_queries.py
detech_query_pkg/dynamodb_pkg/utils/__init__.py
detech_query_pkg/dynamodb_pkg/utils/dynamodb_utils.py
detech_query_pkg/timestream_pkg/__init__.py
detech_query_pkg/timestream_pkg/ts_queries.py
detech_query_pkg/timestream_pkg/models/__init__.py
detech_query_pkg/timestream_pkg/models/metrics_model.py
detech_query_pkg/timestream_pkg/utils/__init__.py
detech_query_pkg/timestream_pkg/utils/ts_utils.py
detech_ai_db-0.0.36.dist-info/LICENSE
detech_ai_db-0.0.36.dist-info/METADATA
detech_ai_db-0.0.36.dist-info/WHEEL
detech_ai_db-0.0.36.dist-info/top_level.txt
detech_ai_db-0.0.36.dist-info/RECORD
